{
  "project_info": {
    "project_number": "454361628031",
    "firebase_url": "https://jklieng-866aa.firebaseio.com",
    "project_id": "jklieng-866aa",
    "storage_bucket": "jklieng-866aa.appspot.com"
  },
  "client": [
    {
      "client_info": {
        "mobilesdk_app_id": "1:454361628031:android:10214a4ed4fc7333",
        "android_client_info": {
          "package_name": "com.jkstudiogroup.lieng"
        }
      },
      "oauth_client": [
        {
          "client_id": "454361628031-los1hkgtka5a0hqmk9gn35j04a2vkhsk.apps.googleusercontent.com",
          "client_type": 3
        }
      ],
      "api_key": [
        {
          "current_key": "AIzaSyCgncaE0E3bQ0SUxZHCjgbXGFMKsGZYd6M"
        }
      ],
      "services": {
        "appinvite_service": {
          "other_platform_oauth_client": [
            {
              "client_id": "454361628031-los1hkgtka5a0hqmk9gn35j04a2vkhsk.apps.googleusercontent.com",
              "client_type": 3
            }
          ]
        }
      }
    }
  ],
  "configuration_version": "1"
}